{"note":"This file is an internal implementation detail to speed up HTML report generation. Its format can change at any time. You might be looking for the JSON report: https://coverage.rtfd.io/cmd.html#cmd-json","format":5,"version":"7.6.4","globals":"85a8ca624da65bc85cd3a5d31c41dcab","files":{"z_8fd9404d70742e9d_calendar_service_py":{"hash":"d45deed98517eac362610fa622ce8398","index":{"url":"z_8fd9404d70742e9d_calendar_service_py.html","file":"calendar_service/calendar_service.py","description":"","nums":{"precision":0,"n_files":1,"n_statements":145,"n_excluded":1,"n_missing":106,"n_branches":34,"n_partial_branches":0,"n_missing_branches":30}}},"z_8fd9404d70742e9d_test_date_usage_py":{"hash":"a6d0aeabc4650d13b8e6232e69a1a94f","index":{"url":"z_8fd9404d70742e9d_test_date_usage_py.html","file":"calendar_service/test_date_usage.py","description":"","nums":{"precision":0,"n_files":1,"n_statements":22,"n_excluded":2,"n_missing":0,"n_branches":0,"n_partial_branches":0,"n_missing_branches":0}}},"client_secret_env_py":{"hash":"4fbb6a7d99c2160d03656cea865978cd","index":{"url":"client_secret_env_py.html","file":"client_secret_env.py","description":"","nums":{"precision":0,"n_files":1,"n_statements":2,"n_excluded":0,"n_missing":0,"n_branches":0,"n_partial_branches":0,"n_missing_branches":0}}},"z_5e94f9a5c9f4c483_chu_nantes_py":{"hash":"41e076b13f283a4b148e77f17c7fe74f","index":{"url":"z_5e94f9a5c9f4c483_chu_nantes_py.html","file":"days_types/chu_nantes.py","description":"","nums":{"precision":0,"n_files":1,"n_statements":3,"n_excluded":0,"n_missing":0,"n_branches":0,"n_partial_branches":0,"n_missing_branches":0}}},"z_3b8eb2d15496cf75_test_event_content_py":{"hash":"7d848a9d3d41ae1a96e75d02183666f4","index":{"url":"z_3b8eb2d15496cf75_test_event_content_py.html","file":"workdays/test_event_content.py","description":"","nums":{"precision":0,"n_files":1,"n_statements":11,"n_excluded":2,"n_missing":0,"n_branches":0,"n_partial_branches":0,"n_missing_branches":0}}},"z_3b8eb2d15496cf75_test_event_manager_py":{"hash":"2df4effc266af2d58f9552dc98197c30","index":{"url":"z_3b8eb2d15496cf75_test_event_manager_py.html","file":"workdays/test_event_manager.py","description":"","nums":{"precision":0,"n_files":1,"n_statements":45,"n_excluded":2,"n_missing":0,"n_branches":0,"n_partial_branches":0,"n_missing_branches":0}}},"z_3b8eb2d15496cf75_workdays_py":{"hash":"4a9ad9d53d577b0d9b4961756f4a3094","index":{"url":"z_3b8eb2d15496cf75_workdays_py.html","file":"workdays/workdays.py","description":"","nums":{"precision":0,"n_files":1,"n_statements":29,"n_excluded":0,"n_missing":0,"n_branches":6,"n_partial_branches":0,"n_missing_branches":0}}}}}